{
  "1": {
    "id": 1,
    "name": "Locro",
    "difficult": [2, 2, 1, 3],
    "duration_time": [10, 20, 45, 10, 45, 1, 6, 2, 39],
    "url_image": "https://encrypted-tbn0.gstatic.com/images?q=tbn:ANd9GcRl4ZQOFDu9v_7zqSDFcYua6XqhHKMTs4nGJP_GUdegZsFjBhS0",
    "quality": [1, 3, 3, 3, 1, 3, 3, 3, 3, 3, 3],
    "preparation": "trituras un zapallo y le metes muchas verduras, fin.",
    "author": 1
  },
  "1553207196": {
    "id": 1553207196,
    "name": "Sergio",
    "difficult": [
      1
    ],
    "duration_time": [
      440
    ],
    "url_image": "http://sergio.com",
    "preparation": "developing",
    "quality": []
  },
  "1553207443": {
    "id": 1553207443,
    "name": "carlos",
    "difficult": [
      3
    ],
    "duration_time": [
      4000
    ],
    "url_image": "http://pollitoconpapas.com",
    "preparation": "asjfjasjfjasfjasf",
    "quality": []
  }
}